Workbook

Sheet Test Cases
A1: Test ID | B1: Category | C1: Workflow Name | D1: Priority | E1: Preconditions / Steps | F1: Expected Result | G1: Status | H1: Actual Result / Notes | I1: Tested By | J1: Date
A2: TC-01 | B2: Uniqueness & Registration Validation | C2: Duplicate vehicle rejection | D2: High | E2: 1) Register vehicle 'Van-05' (reg VAN-005). 2) Attempt to register a second vehicle using reg number VAN-005. | F2: System blocks the second registration with a 'duplicate registration number' error. | G2: Not Tested
A3: TC-02 | B3: Uniqueness & Registration Validation | C3: Required field validation | D3: Medium | E3: Try registering a vehicle with no Max Load Capacity, or a negative value. | F3: Form validation rejects submission before it reaches the database. | G3: Not Tested
A4: TC-03 | B4: Driver Eligibility Rules | C4: Expired license blocks assignment | D4: High | E4: 1) Register driver 'Sam' with License Expiry Date = yesterday. 2) Try to assign Sam to a new trip. | F4: Sam does not appear in the driver dropdown, or assignment is rejected with an 'expired license' error. | G4: Not Tested
A5: TC-04 | B5: Driver Eligibility Rules | C5: Suspended driver blocked | D5: High | E5: 1) Set driver 'Riya' status = Suspended (Safety Officer role). 2) Attempt to assign Riya to a trip. | F5: Riya is excluded from the driver selection pool. | G5: Not Tested
A6: TC-05 | B6: Driver Eligibility Rules | C6: Double-booking a driver | D6: High | E6: 1) Dispatch a trip with driver 'Alex' (status -> On Trip). 2) Create a second trip and try to assign Alex again. | F6: Alex is not selectable, or the second assignment is rejected. | G6: Not Tested
A7: TC-06 | B7: Vehicle Eligibility Rules | C7: Vehicle in shop excluded from dispatch | D7: High | E7: 1) Create an active maintenance record for 'Van-05' (status auto -> In Shop). 2) Attempt to create a trip and select Van-05. | F7: Van-05 does not appear in the vehicle dropdown. | G7: Not Tested
A8: TC-07 | B8: Vehicle Eligibility Rules | C8: Retired vehicle permanently excluded | D8: High | E8: 1) Set a vehicle status to Retired. 2) Try to dispatch it. 3) Add it to a maintenance log, then close that log. | F8: Vehicle excluded from dispatch at all times; after closing maintenance it stays Retired (not reverted to Available). | G8: Not Tested
A9: TC-08 | B9: Vehicle Eligibility Rules | C9: Double-booking a vehicle | D9: High | E9: 1) Dispatch Van-05 on Trip A (status -> On Trip). 2) Attempt to assign Van-05 to Trip B before Trip A completes. | F9: Assignment to Trip B is rejected. | G9: Not Tested
A10: TC-09 | B10: Cargo Weight Validation | C10: Overweight cargo rejected | D10: High | E10: Van-05 max capacity = 500kg. Create a trip with Cargo Weight = 600kg. | F10: System blocks trip creation/dispatch with a capacity-exceeded error. | G10: Not Tested
A11: TC-10 | B11: Cargo Weight Validation | C11: Boundary case: cargo equals max capacity | D11: Medium | E11: Create a trip with Cargo Weight = exactly 500kg (equal to max capacity). | F11: Trip is allowed (rule is 'must not exceed', so equal should pass). | G11: Not Tested
A12: TC-11 | B12: Trip Lifecycle & Status Cascades | C12: Full happy path | D12: High | E12: 1) Register Van-05 (Available) and driver Alex (Available, valid license). 2) Create trip, Cargo=450kg -> Draft. 3) Dispatch -> both flip to On Trip. 4) Complete trip (enter odometer + fuel) -> both flip back to Available. | F12: Odometer updates on vehicle record; trip status = Completed; vehicle & driver = Available. | G12: Not Tested
A13: TC-12 | B13: Trip Lifecycle & Status Cascades | C13: Cancellation restores availability | D13: High | E13: 1) Dispatch a trip (vehicle/driver -> On Trip). 2) Cancel the dispatched trip. | F13: Vehicle and driver both revert to Available (not stuck On Trip). | G13: Not Tested
... A22: TC-21 | B22: Dashboard / KPI Consistency | C22: KPI accuracy after state changes | D22: Medium | E22: 1) Note starting KPI counts. 2) Dispatch a trip, then put another vehicle into maintenance. | F22: Available Vehicles drops by 2; Vehicles in Maintenance rises by 1; Active Trips rises by 1. | G22: Not Tested

Sheet Role Edge Cases
A1: Edge Case ID | B1: Role | C1: Edge Case | D1: Priority | E1: Preconditions / Steps | F1: Expected Result | G1: Status | H1: Actual Result / Notes | I1: Tested By | J1: Date
A2: EC-01 | B2: Fleet Manager | C2: Retire a vehicle currently On Trip | D2: High | E2: Attempt to set a vehicle's status to Retired while it is mid-trip (On Trip). | F2: System blocks retirement until the trip is Completed or Cancelled, or forces the trip to resolve first. | G2: Not Tested
A3: EC-02 | B3: Fleet Manager | C3: Retire a vehicle with an open maintenance record | D3: Medium | E3: Attempt to retire a vehicle that has an active (unclosed) maintenance record. | F3: System either blocks retirement until maintenance is closed, or auto-closes it and logs the action — behavior must be explicit, not silent. | G3: Not Tested
A4: EC-03 | B4: Fleet Manager | C4: Case/whitespace duplicate registration number | D4: High | E4: Register 'VAN-005', then attempt to register 'van-005' or 'VAN-005 ' (trailing space). | F4: Rejected as a duplicate; uniqueness check is case-insensitive and trims whitespace. | G4: Not Tested
A5: EC-04 | B5: Fleet Manager | C5: Odometer rollback | D5: High | E5: Edit a vehicle's odometer to a value lower than its current recorded reading. | F5: System rejects the edit — odometer should only increase. | G5: Not Tested
A6: EC-05 | B6: Fleet Manager | C6: Delete a vehicle with trip/expense history | D6: High | E6: Attempt to permanently delete a vehicle that has past trips, fuel logs, or maintenance records. | F6: Hard delete is blocked; system allows soft-delete/Retired status only, preserving historical records. | G6: Not Tested
A7: EC-06 | B7: Fleet Manager | C7: Maintenance record with end date before start date | D7: Medium | E7: Create a maintenance record where the completion date precedes the start date. | F7: Form validation rejects the date range. | G7: Not Tested
A8: EC-07 | B8: Fleet Manager | C8: Close maintenance that's already closed | D8: Low | E8: Attempt to close a maintenance record that has no active/open status. | F8: System shows a no-op message or disables the action; no duplicate status change fires. | G8: Not Tested
A9: EC-08 | B9: Fleet Manager | C9: Zero or negative acquisition cost | D9: Medium | E9: Register a vehicle with Acquisition Cost = 0 or a negative number. | F9: Rejected — acquisition cost must be a positive value (also prevents divide-by-zero in ROI reports). | G9: Not Tested
A10: EC-09 | B10: Fleet Manager | C10: Bulk import with internal duplicates | D10: Medium | E10: Import a CSV of vehicles where two rows share the same registration number. | F10: Import fails or partially succeeds with a clear per-row error identifying the duplicate. | G10: Not Tested
A11: EC-10 | B11: Driver | C11: Trip with identical source and destination | D11: Medium | E11: Create a trip where Source = Destination. | F11: System rejects the trip or requires confirmation, since a zero-distance trip is likely a data-entry error. | G11: Not Tested
A12: EC-11 | B12: Driver | C12: Zero or negative cargo weight | D12: High | E12: Create a trip with Cargo Weight = 0 or a negative number. | F12: Rejected — cargo weight must be a positive value. | G12: Not Tested
A13: EC-12 | B13: Driver | C13: Zero or negative planned distance | D13: Medium | E13: Create a trip with Planned Distance = 0 or negative. | F13: Rejected with a validation error. | G13: Not Tested
... A39: EC-38 | B39: Cross-Role / System | C39: Timezone boundary on date-based logs | D39: Low | E39: Log a fuel entry or complete a trip near midnight in the user's local timezone, near a UTC day boundary. | F39: Date stored reflects the user's local date consistently across create, edit, and reporting views. | G39: Not Tested

Sheet Summary
A1: TransitOps – QA Test Summary
A3: Metric | B3: Count | D3: Category | E3: # Cases | F3: # Passed
A4: Total Test Cases | B4: =COUNTA('Test Cases'!A2:A22) -> 21 | D4: Uniqueness & Registration Validation | E4: =COUNTIF('Test Cases'!$B$2:$B$22,D4) -> 2 | F4: =COUNTIFS('Test Cases'!$B$2:$B$22,D4,'Test Cases'!$G$2:$G$22,"Pass") -> 0
A5: Passed | B5: =COUNTIF('Test Cases'!G2:G22,"Pass") -> 0 | D5: Driver Eligibility Rules | E5: =COUNTIF('Test Cases'!$B$2:$B$22,D5) -> 3 | F5: =COUNTIFS('Test Cases'!$B$2:$B$22,D5,'Test Cases'!$G$2:$G$22,"Pass") -> 0
A6: Failed | B6: =COUNTIF('Test Cases'!G2:G22,"Fail") -> 0 | D6: Vehicle Eligibility Rules | E6: =COUNTIF('Test Cases'!$B$2:$B$22,D6) -> 3 | F6: =COUNTIFS('Test Cases'!$B$2:$B$22,D6,'Test Cases'!$G$2:$G$22,"Pass") -> 0
A7: Blocked | B7: =COUNTIF('Test Cases'!G2:G22,"Blocked") -> 0 | D7: Cargo Weight Validation | E7: =COUNTIF('Test Cases'!$B$2:$B$22,D7) -> 2 | F7: =COUNTIFS('Test Cases'!$B$2:$B$22,D7,'Test Cases'!$G$2:$G$22,"Pass") -> 0
A8: Not Tested | B8: =COUNTIF('Test Cases'!G2:G22,"Not Tested") -> 21 | D8: Trip Lifecycle & Status Cascades | E8: =COUNTIF('Test Cases'!$B$2:$B$22,D8) -> 3 | F8: =COUNTIFS('Test Cases'!$B$2:$B$22,D8,'Test Cases'!$G$2:$G$22,"Pass") -> 0
A9: High Priority Cases | B9: =COUNTIF('Test Cases'!D2:D22,"High") -> 14 | D9: Maintenance Workflow | E9: =COUNTIF('Test Cases'!$B$2:$B$22,D9) -> 2 | F9: =COUNTIFS('Test Cases'!$B$2:$B$22,D9,'Test Cases'!$G$2:$G$22,"Pass") -> 0
A10: Pass Rate | B10: =IFERROR(B4/B3,0) -> 0 | D10: Fuel, Expense & Cost Calculations | E10: =COUNTIF('Test Cases'!$B$2:$B$22,D10) -> 3 | F10: =COUNTIFS('Test Cases'!$B$2:$B$22,D10,'Test Cases'!$G$2:$G$22,"Pass") -> 0
D11: RBAC / Access Control | E11: =COUNTIF('Test Cases'!$B$2:$B$22,D11) -> 2 | F11: =COUNTIFS('Test Cases'!$B$2:$B$22,D11,'Test Cases'!$G$2:$G$22,"Pass") -> 0
D12: Dashboard / KPI Consistency | E12: =COUNTIF('Test Cases'!$B$2:$B$22,D12) -> 1 | F12: =COUNTIFS('Test Cases'!$B$2:$B$22,D12,'Test Cases'!$G$2:$G$22,"Pass") -> 0
A13: Role Edge Cases – QA Summary
A14: Metric | B14: Count | D14: Role | E14: # Edge Cases | F14: # Passed
A15: Total Edge Cases | B15: =COUNTA('Role Edge Cases'!A2:A39) -> 38 | D15: Fleet Manager | E15: =COUNTIF('Role Edge Cases'!$B$2:$B$39,D15) -> 9 | F15: =COUNTIFS('Role Edge Cases'!$B$2:$B$39,D15,'Role Edge Cases'!$G$2:$G$39,"Pass") -> 0
A16: Passed | B16: =COUNTIF('Role Edge Cases'!G2:G39,"Pass") -> 0 | D16: Driver | E16: =COUNTIF('Role Edge Cases'!$B$2:$B$39,D16) -> 10 | F16: =COUNTIFS('Role Edge Cases'!$B$2:$B$39,D16,'Role Edge Cases'!$G$2:$G$39,"Pass") -> 0
A17: Failed | B17: =COUNTIF('Role Edge Cases'!G2:G39,"Fail") -> 0 | D17: Safety Officer | E17: =COUNTIF('Role Edge Cases'!$B$2:$B$39,D17) -> 6 | F17: =COUNTIFS('Role Edge Cases'!$B$2:$B$39,D17,'Role Edge Cases'!$G$2:$G$39,"Pass") -> 0
A18: Blocked | B18: =COUNTIF('Role Edge Cases'!G2:G39,"Blocked") -> 0 | D18: Financial Analyst | E18: =COUNTIF('Role Edge Cases'!$B$2:$B$39,D18) -> 9 | F18: =COUNTIFS('Role Edge Cases'!$B$2:$B$39,D18,'Role Edge Cases'!$G$2:$G$39,"Pass") -> 0
A19: Not Tested | B19: =COUNTIF('Role Edge Cases'!G2:G39,"Not Tested") -> 38 | D19: Cross-Role / System | E19: =COUNTIF('Role Edge Cases'!$B$2:$B$39,D19) -> 4 | F19: =COUNTIFS('Role Edge Cases'!$B$2:$B$39,D19,'Role Edge Cases'!$G$2:$G$39,"Pass") -> 0
